LICENSE.txt
MANIFEST.in
README.md
VERSION.txt
pyproject.toml
setup.cfg
setup.py
version.py
flyr/__init__.py
flyr/camera_metadata.py
flyr/embedded_image.py
flyr/flyr.py
flyr/image_manipulation.py
flyr/measurement_info.py
flyr/normalization.py
flyr/palette_info.py
flyr/picture_in_picture.py
flyr/records.py
flyr/thermal.py
flyr/thermogram.py
flyr.egg-info/PKG-INFO
flyr.egg-info/SOURCES.txt
flyr.egg-info/dependency_links.txt
flyr.egg-info/entry_points.txt
flyr.egg-info/requires.txt
flyr.egg-info/top_level.txt
flyr/palettes/__init__.py
flyr/palettes/cividis.py
flyr/palettes/copper.py
flyr/palettes/embedded.py
flyr/palettes/gist_earth.py
flyr/palettes/gist_rainbow.py
flyr/palettes/hot.py
flyr/palettes/inferno.py
flyr/palettes/jet.py
flyr/palettes/magma.py
flyr/palettes/ocean.py
flyr/palettes/plasma.py
flyr/palettes/rainbow.py
flyr/palettes/terrain.py
flyr/palettes/turbo.py
flyr/palettes/viridis.py