Metadata-Version: 2.4
Name: flyr
Version: 3.4.1
Summary: Flyr is a library for extracting thermal data from FLIR images written fully in Python, without depending on ExifTool.
Home-page: https://bitbucket.org/nimmerwoner/flyr/
Download-URL: https://bitbucket.org/nimmerwoner/flyr/downloads/flyr-3.4.1.tar.gz
Author: Arthur Nieuwland
Author-email: anieuwland@nimmerfort.eu
License: EUPL v1.2
Project-URL: Issues, https://bitbucket.org/nimmerwoner/flyr/issues?status=new&status=open
Project-URL: Releases, https://bitbucket.org/nimmerwoner/flyr/downloads/
Project-URL: Author website, http://nimmerfort.eu
Keywords: flir,thermography,heat imagery
Classifier: Intended Audience :: Developers
Classifier: Intended Audience :: Information Technology
Classifier: Intended Audience :: Science/Research
Classifier: License :: OSI Approved :: European Union Public Licence 1.2 (EUPL 1.2)
Classifier: Operating System :: OS Independent
Classifier: Programming Language :: Python :: 3
Classifier: Programming Language :: Python :: 3.6
Classifier: Programming Language :: Python :: 3.7
Classifier: Programming Language :: Python :: 3.8
Classifier: Programming Language :: Python :: 3.9
Classifier: Programming Language :: Python :: 3.10
Classifier: Programming Language :: Python :: 3.11
Classifier: Programming Language :: Python :: 3.12
Classifier: Programming Language :: Python :: 3.13
Classifier: Topic :: Multimedia :: Graphics
Classifier: Topic :: Scientific/Engineering
Classifier: Topic :: Scientific/Engineering :: Physics
Classifier: Topic :: Software Development :: Libraries
Classifier: Topic :: Software Development :: Libraries :: Python Modules
Classifier: Typing :: Typed
Requires-Python: >=3.6
License-File: LICENSE.txt
Requires-Dist: numpy
Requires-Dist: nptyping==0.3.1
Requires-Dist: pillow
Dynamic: author
Dynamic: author-email
Dynamic: classifier
Dynamic: description
Dynamic: description-content-type
Dynamic: download-url
Dynamic: home-page
Dynamic: keywords
Dynamic: license
Dynamic: license-file
Dynamic: project-url
Dynamic: requires-dist
Dynamic: requires-python
Dynamic: summary
